{
    "string":[
        {
            "name":"USB_hint_cancel",
            "value":"確定",
            "attr":{
                "priority":"LT"
            }
        },
        {
            "name":"usb_right_title",
            "value":"USB 存取授權",
            "attr":{
                "priority":"LT"
            }
        },
        {
            "name":"USB_hint",
            "value":"USB 連接方式",
            "attr":{
                "priority":"LT"
            }
        },
        {
            "name":"notAllowButton",
            "value":"不允許",
            "attr":{
                "priority":"LT"
            }
        },
        {
            "name":"USB_func_charge",
            "value":"只充電",
            "attr":{
                "priority":"LT"
            }
        },
        {
            "name":"allowButton",
            "value":"允許",
            "attr":{
                "priority":"LT"
            }
        },
        {
            "name":"usb_right_content",
            "value":"是否允許 %1$s 使用%2$s？",
            "attr":{
                "priority":"LT"
            }
        }
    ]
}