{
  "string": [
    {
      "name": "allowButton",
      "value": "Allow"
    },
    {
      "name": "notAllowButton",
      "value": "Not Allow"
    },
    {
      "name": "allow",
      "value": "Whether "
    },
    {
      "name": "use",
      "value": " allowed to use the "
    },
    {
      "name": "notification_title",
      "value": "Mass Stroage"
    },
    {
      "name": "notification_text",
      "value": "Usb stroage device connectd"
    },
    {
      "name": "notification_button",
      "value": "Check "
    },
    {
      "name": "notification_label",
      "value": "filemanager"
    },
    {
      "name": "permission_reason",
      "value": "allow send notirycation in foreground and background"
    },
    {
      "name": "USB_hint",
      "value": "USB Connected"
    },
    {
      "name": "USB_func_charge",
      "value": "Charge Only"
    },
    {
      "name": "USB_func_mtp",
      "value": "Transfer File(MTP)"
    },
    {
      "name": "USB_func_ptp",
      "value": "Transfer Picture(PTP)"
    },
    {
      "name": "USB_hint_cancel",
      "value": "Cancel"
    },
    {
      "name": "USB_notify_charge_title",
      "value": "Charge only"
    },
    {
      "name": "USB_notify_mtp_title",
      "value": "Mtp only"
    },
    {
      "name": "USB_notify_ptp_title",
      "value": "Ptp only"
    },
    {
      "name": "USB_notify_text",
      "value": "Touch for more option"
    }
  ]
}